dictmsgr/__init__.py
dictmsgr-0.2.dist-info/LICENSE
dictmsgr-0.2.dist-info/METADATA
dictmsgr-0.2.dist-info/WHEEL
dictmsgr-0.2.dist-info/top_level.txt
dictmsgr-0.2.dist-info/RECORD
