Metadata-Version: 2.1
Name: dictmsgr
Version: 0.2
Summary: Single-thread dict-based messenger inspired by the Robot Operation System.
Keywords: dict,messenger
Classifier: Development Status :: 5 - Production/Stable
Classifier: Environment :: Console
Classifier: Intended Audience :: Science/Research
Classifier: Operating System :: OS Independent
Classifier: Programming Language :: Python :: 3
Requires-Python: >=3.7
License-File: LICENSE
